flask_csv.py
Flask_CSV-1.2.1.dist-info/LICENSE
Flask_CSV-1.2.1.dist-info/METADATA
Flask_CSV-1.2.1.dist-info/WHEEL
Flask_CSV-1.2.1.dist-info/top_level.txt
Flask_CSV-1.2.1.dist-info/RECORD
