Metadata-Version: 2.1
Name: Flask-CSV
Version: 1.2.1
Summary: Easily render CSVs within any flask application
Home-page: https://github.com/Shir0kamii/Flask-CSV
Download-URL: https://github.com/Shir0kamii/Flask-CSV/tags
Author-email: shir0kamii@gmail.com
Platform: any
Classifier: Programming Language :: Python
Classifier: Programming Language :: Python :: 3.4
Classifier: Programming Language :: Python :: 3.5
License-File: LICENSE
Requires-Dist: csvalidate
Requires-Dist: Flask
Requires-Dist: marshmallow
